steamed/__init__.py
steamed/client.py
steamed/confirmation.py
steamed/constants.py
steamed/exceptions.py
steamed/guard.py
steamed/login.py
steamed/market.py
steamed/models.py
steamed/session.py
steamed/utils.py
steamed-0.1.1.dist-info/LICENSE
steamed-0.1.1.dist-info/METADATA
steamed-0.1.1.dist-info/WHEEL
steamed-0.1.1.dist-info/top_level.txt
steamed-0.1.1.dist-info/RECORD
