Metadata-Version: 2.1
Name: steamed
Version: 0.1.1
Summary: A wrapper around Steam official and unofficial APIs
Author: Emanuele Sarte
License: MIT
Project-URL: Homepage, https://github.com/EmanueleSarte/steamed
Project-URL: Bug Tracker, https://github.com/EmanueleSarte/steamed/issues
Keywords: steam
Requires-Python: >=3.8
License-File: LICENSE
Requires-Dist: requests
Requires-Dist: rsa
Requires-Dist: beautifulsoup4
